pddl2gym/__init__.py
pddl2gym-0.0.1.dist-info/WHEEL
pddl2gym-0.0.1.dist-info/METADATA
pddl2gym-0.0.1.dist-info/RECORD
