Metadata-Version: 2.1
Name: pddl2gym
Version: 0.0.1
Summary: A translator from PDDL domain/problem files to OpenAI Gym environment.
License: MIT
Author: MarcoFavorito
Author-email: marco.favorito@gmail.com
Requires-Python: >=3.7,<4.0
Classifier: License :: OSI Approved :: MIT License
Classifier: Programming Language :: Python :: 3
Classifier: Programming Language :: Python :: 3.7
Classifier: Programming Language :: Python :: 3.8
